<?xml version="1.0" encoding="utf-8" ?>
<elements>
	<info>
		<name>Assassino</name>
		<description>A subclasse Assassino do Livro do Jogador 2024.</description>
		<author url="https://dndstore.wizards.com/us/en/product/1001494/2024-player-s-handbook-digital-plus-physical-bundle">Wizards of the Coast</author>
		<update version="0.0.1">
			<file name="rogue-assassin.xml" url="https://raw.githubusercontent.com/AuroraLegacy/elements/master/core/players-handbook-2024/archetypes/rogue-assassin.xml" />
		</update>
	</info>

	<element name="Assassino" type="Archetype" source="Player’s Handbook (2024)" id="ID_WOTC_PHB24_ARCHETYPE_ROGUE_ASSASSIN">
		<supports>Rogue Subclass</supports>
		<description>
			<p class="flavor">Pratique a Sinistra Arte da Morte</p>
			<p>O treinamento de um Assassino foca no uso da furtividade, venenos e disfarces para eliminar os inimigos com eficiência mortal. Enquanto alguns Ladinos que seguem esse caminho são assassinos de aluguel, espiões ou caçadores de recompensa, as capacidades dessa subclasse são igualmente úteis para aventureiros lidando com uma variedade de oponentes monstruosos.</p>
			<div element="ID_WOTC_PHB24_ARCHETYPE_FEATURE_ROGUE_ASSASSIN_ASSASSINATE" />
			<div element="ID_WOTC_PHB24_ARCHETYPE_FEATURE_ROGUE_ASSASSIN_ASSASSINS_TOOLS" />
			<div element="ID_WOTC_PHB24_ARCHETYPE_FEATURE_ROGUE_ASSASSIN_INFILTRATION_EXPERTISE" />
			<div element="ID_WOTC_PHB24_ARCHETYPE_FEATURE_ROGUE_ASSASSIN_ENVENOM_WEAPONS" />
			<div element="ID_WOTC_PHB24_ARCHETYPE_FEATURE_ROGUE_ASSASSIN_DEATH_STRIKE" />
		</description>
		<sheet display="false" />
		<rules>
			<grant type="Archetype Feature" id="ID_WOTC_PHB24_ARCHETYPE_FEATURE_ROGUE_ASSASSIN_ASSASSINATE" level="3"/>
			<grant type="Archetype Feature" id="ID_WOTC_PHB24_ARCHETYPE_FEATURE_ROGUE_ASSASSIN_ASSASSINS_TOOLS" level="3"/>
			<grant type="Archetype Feature" id="ID_WOTC_PHB24_ARCHETYPE_FEATURE_ROGUE_ASSASSIN_INFILTRATION_EXPERTISE" level="9"/>
			<grant type="Archetype Feature" id="ID_WOTC_PHB24_ARCHETYPE_FEATURE_ROGUE_ASSASSIN_ENVENOM_WEAPONS" level="13"/>
			<grant type="Archetype Feature" id="ID_WOTC_PHB24_ARCHETYPE_FEATURE_ROGUE_ASSASSIN_DEATH_STRIKE" level="17"/>
		</rules>
	</element>

	<element name="Nível 3: Assassinar" type="Archetype Feature" source="Player’s Handbook (2024)" id="ID_WOTC_PHB24_ARCHETYPE_FEATURE_ROGUE_ASSASSIN_ASSASSINATE">
		<requirements>!ID_INTERNAL_PHB24_FEATURE_REPLACEMENT_ROGUE_ASSASSIN_ASSASSINATE</requirements>
		<description>
			<p>Você é hábil em emboscar um alvo, ganhando os seguintes benefícios:</p>
			<p class="indent"><em><strong>Iniciativa.</strong></em> Você tem Vantagem em rolagens de Iniciativa.</p>
			<p class="indent"><em><strong>Golpes Surpresa.</strong></em> Durante a primeira rodada de cada combate, você tem Vantagem nas jogadas de ataque contra qualquer criatura que não tenha jogado seu turno. Se seu Ataque Furtivo atingir um alvo durante essa rodada, o alvo sofre dano extra do mesmo tipo da arma igual ao seu nível de Ladino.</p>
		</description>
		<sheet alt="Assassinar">
			<description>Na primeira rodada do combate, você tem Vantagem em jogadas de ataque contra qualquer criatura que não tenha agido ainda no combate, e seu Ataque Furtivo causa um dano adicional de {{level:rogue}}.</description>
		</sheet>
		<rules>
			<grant type="Grants" id="ID_INTERNAL_GRANTS_INITIATIVE_ADVANTAGE" />
		</rules>
	</element>

	<element name="Nível 3: Ferramentas de Assassino" type="Archetype Feature" source="Player’s Handbook (2024)" id="ID_WOTC_PHB24_ARCHETYPE_FEATURE_ROGUE_ASSASSIN_ASSASSINS_TOOLS">
		<requirements>!ID_INTERNAL_PHB24_FEATURE_REPLACEMENT_ROGUE_ASSASSIN_ASSASSINS_TOOLS</requirements>
		<description>
			<p>Você ganha um Kit de Disfarce e um Kit de Envenenador, e você possui proficiência com eles.</p>
		</description>
		<sheet display="false"/>
		<rules>
			<grant type="Proficiency" id="ID_PROFICIENCY_TOOL_PROFICIENCY_DISGUISE_KIT" />
			<grant type="Proficiency" id="ID_PROFICIENCY_TOOL_PROFICIENCY_POISONERS_KIT" />
		</rules>
	</element>

	<element name="Nível 9: Especialidade em Infiltração" type="Archetype Feature" source="Player’s Handbook (2024)" id="ID_WOTC_PHB24_ARCHETYPE_FEATURE_ROGUE_ASSASSIN_INFILTRATION_EXPERTISE">
		<requirements>!ID_INTERNAL_PHB24_FEATURE_REPLACEMENT_ROGUE_ASSASSIN_INFILTRATION_EXPERTISE</requirements>
		<description>
			<p>Você é especialista nas seguintes técnicas que auxiliam as suas infiltrações.</p>
			<p class="indent"><em><strong>Mimetismo Magistral.</strong></em> Você consegue imitar de forma infalível a fala de outra pessoa, sua caligrafia, ou ambas, caso tenha passado pelo menos 1 hora as estudando.</p>
			<p class="indent"><em><strong>Mira Itinerante.</strong></em> Seu Deslocamento não se reduz a 0 ao usar a Mira Estável.</p>
		</description>
		<sheet alt="Especialidade em Infiltração">
			<description>Você pode imitar com perfeição a fala e a caligrafia de outra pessoa após estudá-las por 1 hora. Além disso, usar Mira Estável não reduz o seu Deslocamento para 0.</description>
		</sheet>
	</element>

	<element name="Nível 13: Envenenar Armas" type="Archetype Feature" source="Player’s Handbook (2024)" id="ID_WOTC_PHB24_ARCHETYPE_FEATURE_ROGUE_ASSASSIN_ENVENOM_WEAPONS">
		<requirements>!ID_INTERNAL_PHB24_FEATURE_REPLACEMENT_ROGUE_ASSASSIN_ENVENOM_WEAPONS</requirements>
		<description>
			<p>Quando usar a opção Envenenar do seu Ataque Astuto, o alvo também sofre 2d6 de dano de Veneno sempre que falhar no teste de resistência. Esse dano ignora Resistência a dano de Veneno.</p>
		</description>
		<sheet alt="Envenenar Armas">
			<description>Quando usar a opção Envenenar do Ataque Astuto, o alvo toma 2d6 de dano de Veneno adicional quando falha no teste de resistência. Esse dano ignora Resistência a Veneno.</description>
		</sheet>
		<rules>
			<grant type="Grants" id="ID_INTERNAL_PHB24_FEATURE_REPLACEMENT_ROGUE_CUNNING_STRIKE_POISON" />
		</rules>
	</element>
	<element name="Envenenar (Custo: 1d6)" type="Archetype Feature" source="Player’s Handbook (2024)" id="ID_WOTC_PHB24_ARCHETYPE_FEATURE_ROGUE_ASSASSIN_ENVENOM_WEAPONS_POISON">
		<supports>PHB24 Cunning Strike Envenom Weapon</supports>
		<compendium display="false" />
		<description>
			<p>Quando usar a opção Envenenar do seu Ataque Astuto, o alvo também sofre 2d6 de dano de Veneno sempre que falhar no teste de resistência. Esse dano ignora Resistência a dano de Veneno.</p>
		</description>
		<sheet alt="Envenenar (1d6)">
			<description>O alvo deve ser bem-sucedido num teste de resistência de Constituição CD {{cunning strike:dc}} ou tomará 2d6 de dano de Veneno e ficará Envenenado por 1 minuto. Esse dano ignora Resistência a Veneno. Ao fim de cada turno do alvo, o alvo Envenenado repete o teste de resistência, encerrando o efeito em um sucesso. Para usar, você deve ter um Kit de Envenenador consigo.</description>
		</sheet>
	</element>
	<append id="ID_WOTC_PHB24_CLASS_FEATURE_ROGUE_CUNNING_STRIKE">
		<rules>
			<select type="Archetype Feature" name="Envenom Weapon" supports="PHB24 Cunning Strike Envenom Weapon" default="ID_WOTC_PHB24_ARCHETYPE_FEATURE_ROGUE_ASSASSIN_ENVENOM_WEAPONS_POISON" requirements="ID_WOTC_PHB24_ARCHETYPE_FEATURE_ROGUE_ASSASSIN_ENVENOM_WEAPONS" />
		</rules>
	</append>

	<element name="Nível 17: Golpe Mortal" type="Archetype Feature" source="Player’s Handbook (2024)" id="ID_WOTC_PHB24_ARCHETYPE_FEATURE_ROGUE_ASSASSIN_DEATH_STRIKE">
		<requirements>!ID_INTERNAL_PHB24_FEATURE_REPLACEMENT_ROGUE_ASSASSIN_DEATH_STRIKE</requirements>
		<description>
			<p>Quando atingir um alvo com o seu Ataque Furtivo na primeira rodada de um combate, o alvo deve ter sucesso em um teste de resistência de Constituição (CD 8 mais seu modificador de Destreza e Bônus de Proficiência), ou o dano daquele ataque é dobrado contra ele.</p>
		</description>
		<sheet alt="Golpe Mortal">
			<description>Quando atingir um alvo com Ataque Furtivo na primeira rodada do combate, o alvo deve ter sucesso em um teste de resistência de Constituição CD {{death strike:dc}}, ou o dano do ataque será dobrado.</description>
		</sheet>
		<rules>
			<stat name="death strike:dc" value="8" bonus="base" />
			<stat name="death strike:dc" value="proficiency" bonus="proficiency" />
			<stat name="death strike:dc" value="dexterity:modifier" bonus="ability" />
		</rules>
	</element>
	
	<element name="Assassin’s Tools Feature Replacement" type="Grants" source="Internal" id="ID_INTERNAL_PHB24_FEATURE_REPLACEMENT_ROGUE_ASSASSIN_ASSASSINS_TOOLS" />
	<element name="Assassinate Feature Replacement" type="Grants" source="Internal" id="ID_INTERNAL_PHB24_FEATURE_REPLACEMENT_ROGUE_ASSASSIN_ASSASSINATE" />
	<element name="Infiltration Expertise Feature Replacement" type="Grants" source="Internal" id="ID_INTERNAL_PHB24_FEATURE_REPLACEMENT_ROGUE_ASSASSIN_INFILTRATION_EXPERTISE" />
	<element name="Envenom Weapons Feature Replacement" type="Grants" source="Internal" id="ID_INTERNAL_PHB24_FEATURE_REPLACEMENT_ROGUE_ASSASSIN_ENVENOM_WEAPONS" />
	<element name="Death Strike Feature Replacement" type="Grants" source="Internal" id="ID_INTERNAL_PHB24_FEATURE_REPLACEMENT_ROGUE_ASSASSIN_DEATH_STRIKE" />
</elements>