<?xml version="1.0" encoding="utf-8" ?>
<elements>
	<info>
		<update version="0.0.1">
		<file name="wizard-abjurer.xml" url="https://raw.githubusercontent.com/GabrielKalleb/Arcanotheca/main/core/players-handbook-2024/archetypes/wizard-abjurer.xml" />
		</update>
	</info>

	<element name="Abjurador" type="Archetype" source="Player’s Handbook (2024)" id="ID_WOTC_PHB24_ARCHETYPE_WIZARD_ABJURER">
		<supports>Wizard Subclass</supports>
		<description>
			<p class="flavor">Proteja Companheiros e Bana Inimigos</p>
			<p>Seu estudo de magia se concentra em magias que bloqueiam, banem ou protegem — encerrando efeitos prejudiciais, banindo influências malignas e protegendo os fracos. Abjuradores são procurados quando espíritos malignos exigem exorcismo, quando locais precisam de guarda contra espionagem mágica e quando portais para outros planos de existência devem ser fechados. Grupos de aventureiros valorizam Abjuradores pela proteção que eles provêm contra uma variedade de magias hostis e outros ataques.</p>
            <div element="ID_WOTC_PHB24_ARCHETYPE_WIZARD_ABJURER_ABJURATION_SAVANT" />
			<div element="ID_WOTC_PHB24_ARCHETYPE_WIZARD_ABJURER_ARCANE_WARD" />
			<div element="ID_WOTC_PHB24_ARCHETYPE_WIZARD_ABJURER_PROTECTED_WARD" />
			<div element="ID_WOTC_PHB24_ARCHETYPE_WIZARD_ABJURER_SPELL_BREAKER" />
			<div element="ID_WOTC_PHB24_ARCHETYPE_WIZARD_ABJURER_SPELL_RESISTANCE" />
		</description>
        <sheet display="false" />
		<rules>
			<grant type="Archetype Feature" id="ID_WOTC_PHB24_ARCHETYPE_WIZARD_ABJURER_ABJURATION_SAVANT" level="3"/>
			<grant type="Archetype Feature" id="ID_WOTC_PHB24_ARCHETYPE_WIZARD_ABJURER_ARCANE_WARD" level="3"/>
			<grant type="Archetype Feature" id="ID_WOTC_PHB24_ARCHETYPE_WIZARD_ABJURER_PROTECTED_WARD" level="6"/>
			<grant type="Archetype Feature" id="ID_WOTC_PHB24_ARCHETYPE_WIZARD_ABJURER_SPELL_BREAKER" level="10"/>
			<grant type="Archetype Feature" id="ID_WOTC_PHB24_ARCHETYPE_WIZARD_ABJURER_SPELL_RESISTANCE" level="14"/>
		</rules>
	</element>

	<element name="Nível 3: Sábio da Abjuração" type="Archetype Feature" source="Player’s Handbook (2024)" id="ID_WOTC_PHB24_ARCHETYPE_WIZARD_ABJURER_ABJURATION_SAVANT">
		<requirements>!ID_INTERNAL_PHB24_FEATURE_REPLACEMENT_WIZARD_ABJURER_ABJURATION_SAVANT</requirements>
		<description>
			<p>Escolha duas magias de Mago da escola de Abjuração, cada uma não podendo ser de um nível maior que o 2, e adicione-as ao seu grimório gratuitamente.</p>
			<p class="indent">Além disso, sempre que você ganhar acesso a um novo nível de espaços de magia nesta classe, você pode adicionar gratuitamente uma magia de Mago da escola de Abjuração ao seu grimório. A magia escolhida deve ser de um nível para o qual você tenha espaços de magia.</p>
		</description>
		<sheet display="false" />
		<rules>
			<select type="Spell" name="Abjuration Spell (Abjuration Savant)" supports="$(spellcasting:slots),Abjuration,Wizard" number="2" level="3" spellcasting="Wizard" />
			<select type="Spell" name="Abjuration Spell (Abjuration Savant)" supports="$(spellcasting:slots),Abjuration,Wizard" level="5" spellcasting="Wizard" />
			<select type="Spell" name="Abjuration Spell (Abjuration Savant)" supports="$(spellcasting:slots),Abjuration,Wizard" level="7" spellcasting="Wizard" />
			<select type="Spell" name="Abjuration Spell (Abjuration Savant)" supports="$(spellcasting:slots),Abjuration,Wizard" level="9" spellcasting="Wizard" />
			<select type="Spell" name="Abjuration Spell (Abjuration Savant)" supports="$(spellcasting:slots),Abjuration,Wizard" level="11" spellcasting="Wizard" />
			<select type="Spell" name="Abjuration Spell (Abjuration Savant)" supports="$(spellcasting:slots),Abjuration,Wizard" level="13" spellcasting="Wizard" />
			<select type="Spell" name="Abjuration Spell (Abjuration Savant)" supports="$(spellcasting:slots),Abjuration,Wizard" level="15" spellcasting="Wizard" />
			<select type="Spell" name="Abjuration Spell (Abjuration Savant)" supports="$(spellcasting:slots),Abjuration,Wizard" level="17" spellcasting="Wizard" />
		</rules>
	</element>

	<element name="Nível 3: Proteção Arcana" type="Archetype Feature" source="Player’s Handbook (2024)" id="ID_WOTC_PHB24_ARCHETYPE_WIZARD_ABJURER_ARCANE_WARD">
		<requirements>!ID_INTERNAL_PHB24_FEATURE_REPLACEMENT_WIZARD_ABJURER_ARCANE_WARD</requirements>
		<description>
			<p>Você pode tecer magia ao seu redor para proteção. Quando conjura uma magia de Abjuração com um espaço de magia, pode usar simultaneamente um fio da magia para criar uma proteção mágica em si mesmo que dura até você terminar um Descanso Longo. A proteção tem um máximo de Pontos de Vida igual ao dobro de seu nível de Mago mais seu modificador de Inteligência. Sempre que sofrer dano, a proteção sofre o dano no seu lugar e, se você tiver Resistências ou Vulnerabilidades, aplique-as antes de reduzir os Pontos de Vida da proteção. Se o dano reduzir a proteção a 0 Pontos de Vida, você sofre o dano restante. Enquanto a proteção tiver 0 Pontos de Vida, ela não absorve dano, mas sua magia permanece.</p>
			<p class="indent">Sempre que você conjurar uma magia de Abjuração com um espaço de magia, a proteção recupera um número de Pontos de Vida igual ao dobro do nível do espaço de magia. Alternativamente, como uma Ação Bônus, pode gastar um espaço de magia, e a proteção recupera um número de Pontos de Vida igual ao dobro do nível do espaço gasto.</p>
			<p class="indent">Uma vez que você crie a proteção, não pode criá-la novamente até terminar um Descanso Longo.</p>
		</description>
		<sheet alt="Proteção Arcana" usage="1/Descanso Longo">
			<description>Ao conjurar uma Abjuração com espaço de magia, você ganha uma proteção que dura até um Descanso Longo. A proteção tem PV MÁX de {{arcane ward:hp}}. Quando você sofre dano, aplique suas Resistências/Vulnerabilidades e a proteção absorve o resto. Se ela cair a 0, você sofre o dano excedente; mesmo a 0 PV, a proteção persiste. Sempre que conjurar Abjurações com espaços, a proteção recupera PV igual ao dobro do nível gasto. Como Ação Bônus, pode gastar um espaço de magia e curá-la no dobro do nível do espaço.</description>
		</sheet>
		<rules>
			<stat name="arcane ward:hp" value="level:wizard" bonus="base" />
			<stat name="arcane ward:hp" value="level:wizard" bonus="double" />
			<stat name="arcane ward:hp" value="intelligence:modifier" bonus="ability" />
		</rules>
	</element>

	<element name="Nível 6: Proteção Projetada" type="Archetype Feature" source="Player’s Handbook (2024)" id="ID_WOTC_PHB24_ARCHETYPE_WIZARD_ABJURER_PROTECTED_WARD">
		<requirements>!ID_INTERNAL_PHB24_FEATURE_REPLACEMENT_WIZARD_ABJURER_PROJECTED_WARD</requirements>
		<description>
			<p>Quando uma criatura que você possa ver a até 9 metros (30 pés) de você sofrer dano, você pode usar uma Reação para fazer sua Proteção Arcana absorver esse dano. Se o dano reduzir a proteção a 0 Pontos de Vida, a criatura protegida sofre o dano restante. Se a criatura tiver Resistências ou Vulnerabilidades, aplique-as antes de reduzir os Pontos de Vida da proteção.</p>
		</description>
		<sheet alt="Proteção Projetada" action="Reaction">
			<description>Quando uma criatura visível a até 9m sofre dano, você pode fazer sua Proteção Arcana absorver o dano. Aplique as Resistências/Vulnerabilidades da criatura primeiro. Se a proteção for reduzida a 0 PV, a criatura sofre o resto.</description>
		</sheet>
	</element>

	<element name="Nível 10: Quebrador de Magias" type="Archetype Feature" source="Player’s Handbook (2024)" id="ID_WOTC_PHB24_ARCHETYPE_WIZARD_ABJURER_SPELL_BREAKER">
		<requirements>!ID_INTERNAL_PHB24_FEATURE_REPLACEMENT_WIZARD_ABJURER_SPELL_BREAKER</requirements>
		<description>
			<p>Você sempre tem as magias <i>Contramágica</i> e <i>Dissipar Magia</i> preparadas. Além disso, você pode conjurar <i>Dissipar Magia</i> como uma Ação Bônus, e pode adicionar seu Bônus de Proficiência ao teste de habilidade dela.</p>
			<p class="indent">Quando você conjura qualquer uma das magias com um espaço de magia, aquele espaço não é gasto se a magia falhar em impedir uma magia.</p>
		</description>
		<sheet alt="Quebrador de Magias">
			<description>Pode conjurar Dissipar Magia como Ação Bônus, somando sua Proficiência ao teste. Se ela ou Contramágica falharem em impedir/dissipar, o espaço não é gasto.</description>
		</sheet>
		<rules>		
			<grant type="Spell" id="ID_WOTC_PHB24_SPELL_COUNTERSPELL" level="5" spellcasting="Wizard" prepared="true" />
			<grant type="Spell" id="ID_WOTC_PHB24_SPELL_DISPEL_MAGIC" level="5" spellcasting="Wizard" prepared="true" />
		</rules>
	</element>

	<element name="Nível 14: Resistência a Magia" type="Archetype Feature" source="Player’s Handbook (2024)" id="ID_WOTC_PHB24_ARCHETYPE_WIZARD_ABJURER_SPELL_RESISTANCE">
		<requirements>!ID_INTERNAL_PHB24_FEATURE_REPLACEMENT_WIZARD_ABJURER_SPELL_RESISTANCE</requirements>
		<description>
			<p>Você tem Vantagem em testes de resistência contra magias, e tem Resistência ao dano de magias.</p>
		</description>
		<sheet alt="Resistência a Magia">
			<description>Você tem Vantagem em testes de resistência contra magias e Resistência ao dano delas.</description>
		</sheet>
	</element>
	
	<element name="Abjuration Savant Feature Replacement" type="Grants" source="Internal" id="ID_INTERNAL_PHB24_FEATURE_REPLACEMENT_WIZARD_ABJURER_ABJURATION_SAVANT" />
	<element name="Arcane Ward Feature Replacement" type="Grants" source="Internal" id="ID_INTERNAL_PHB24_FEATURE_REPLACEMENT_WIZARD_ABJURER_ARCANE_WARD" />
	<element name="Projected Ward Feature Replacement" type="Grants" source="Internal" id="ID_INTERNAL_PHB24_FEATURE_REPLACEMENT_WIZARD_ABJURER_PROJECTED_WARD" />
	<element name="Improved Abjuration Feature Replacement" type="Grants" source="Internal" id="ID_INTERNAL_PHB24_FEATURE_REPLACEMENT_WIZARD_ABJURER_SPELL_BREAKER" />
	<element name="Spell Resistance Feature Replacement" type="Grants" source="Internal" id="ID_INTERNAL_PHB24_FEATURE_REPLACEMENT_WIZARD_ABJURER_SPELL_RESISTANCE" />
</elements>